odoo/addons/stock_picking_restrict_cancel_with_orig_move/README.rst
odoo/addons/stock_picking_restrict_cancel_with_orig_move/__init__.py
odoo/addons/stock_picking_restrict_cancel_with_orig_move/__manifest__.py
odoo/addons/stock_picking_restrict_cancel_with_orig_move/i18n/pt_BR.po
odoo/addons/stock_picking_restrict_cancel_with_orig_move/i18n/stock_picking_restrict_cancel_with_orig_move.pot
odoo/addons/stock_picking_restrict_cancel_with_orig_move/models/__init__.py
odoo/addons/stock_picking_restrict_cancel_with_orig_move/models/stock_move.py
odoo/addons/stock_picking_restrict_cancel_with_orig_move/readme/CONTRIBUTORS.rst
odoo/addons/stock_picking_restrict_cancel_with_orig_move/readme/DESCRIPTION.rst
odoo/addons/stock_picking_restrict_cancel_with_orig_move/readme/USAGE.rst
odoo/addons/stock_picking_restrict_cancel_with_orig_move/static/description/icon.png
odoo/addons/stock_picking_restrict_cancel_with_orig_move/static/description/index.html
odoo/addons/stock_picking_restrict_cancel_with_orig_move/tests/__init__.py
odoo/addons/stock_picking_restrict_cancel_with_orig_move/tests/test_restrict_cancel.py
odoo12_addon_stock_picking_restrict_cancel_with_orig_move-12.0.1.0.0.99.dev6.dist-info/METADATA
odoo12_addon_stock_picking_restrict_cancel_with_orig_move-12.0.1.0.0.99.dev6.dist-info/WHEEL
odoo12_addon_stock_picking_restrict_cancel_with_orig_move-12.0.1.0.0.99.dev6.dist-info/top_level.txt
odoo12_addon_stock_picking_restrict_cancel_with_orig_move-12.0.1.0.0.99.dev6.dist-info/RECORD
